ZiyudaShujuZhiSparkRumenjiaochengScalaBan/README.md
ZiyudaShujuZhiSparkRumenjiaochengScalaBan/__init__.py
ZiyudaShujuZhiSparkRumenjiaochengScalaBan/__main__.py
ZiyudaShujuZhiSparkRumenjiaochengScalaBan/file.epub
ZiyudaShujuZhiSparkRumenjiaochengScalaBan/index.html
ZiyudaShujuZhiSparkRumenjiaochengScalaBan/css/__init__.py
ZiyudaShujuZhiSparkRumenjiaochengScalaBan/css/annotations.css
ZiyudaShujuZhiSparkRumenjiaochengScalaBan/css/main.css
ZiyudaShujuZhiSparkRumenjiaochengScalaBan/css/normalize.css
ZiyudaShujuZhiSparkRumenjiaochengScalaBan/css/popup.css
ZiyudaShujuZhiSparkRumenjiaochengScalaBan/font/__init__.py
ZiyudaShujuZhiSparkRumenjiaochengScalaBan/font/fontello.eot
ZiyudaShujuZhiSparkRumenjiaochengScalaBan/font/fontello.svg
ZiyudaShujuZhiSparkRumenjiaochengScalaBan/font/fontello.ttf
ZiyudaShujuZhiSparkRumenjiaochengScalaBan/font/fontello.woff
ZiyudaShujuZhiSparkRumenjiaochengScalaBan/img/__init__.py
ZiyudaShujuZhiSparkRumenjiaochengScalaBan/img/annotator-glyph-sprite.png
ZiyudaShujuZhiSparkRumenjiaochengScalaBan/img/annotator-icon-sprite.png
ZiyudaShujuZhiSparkRumenjiaochengScalaBan/img/apple-touch-icon.png
ZiyudaShujuZhiSparkRumenjiaochengScalaBan/img/cancelfullscreen.png
ZiyudaShujuZhiSparkRumenjiaochengScalaBan/img/close.png
ZiyudaShujuZhiSparkRumenjiaochengScalaBan/img/fullscreen.png
ZiyudaShujuZhiSparkRumenjiaochengScalaBan/img/loader.gif
ZiyudaShujuZhiSparkRumenjiaochengScalaBan/img/menu-icon.png
ZiyudaShujuZhiSparkRumenjiaochengScalaBan/img/save.png
ZiyudaShujuZhiSparkRumenjiaochengScalaBan/img/saved.png
ZiyudaShujuZhiSparkRumenjiaochengScalaBan/img/settings-s.png
ZiyudaShujuZhiSparkRumenjiaochengScalaBan/img/settings.png
ZiyudaShujuZhiSparkRumenjiaochengScalaBan/img/star.png
ZiyudaShujuZhiSparkRumenjiaochengScalaBan/js/__init__.py
ZiyudaShujuZhiSparkRumenjiaochengScalaBan/js/epub.js
ZiyudaShujuZhiSparkRumenjiaochengScalaBan/js/epub.min.js
ZiyudaShujuZhiSparkRumenjiaochengScalaBan/js/epub.min.map
ZiyudaShujuZhiSparkRumenjiaochengScalaBan/js/hooks.min.js
ziyuda_shuju_zhi_spark_rumenjiaocheng_scala_ban-2024.3.5.0.dist-info/METADATA
ziyuda_shuju_zhi_spark_rumenjiaocheng_scala_ban-2024.3.5.0.dist-info/WHEEL
ziyuda_shuju_zhi_spark_rumenjiaocheng_scala_ban-2024.3.5.0.dist-info/entry_points.txt
ziyuda_shuju_zhi_spark_rumenjiaocheng_scala_ban-2024.3.5.0.dist-info/top_level.txt
ziyuda_shuju_zhi_spark_rumenjiaocheng_scala_ban-2024.3.5.0.dist-info/RECORD
